lilliepy_query/__init__.py
lilliepy_query/fetch.py
lilliepy_query/query.py
lilliepy_query-0.1.dist-info/METADATA
lilliepy_query-0.1.dist-info/WHEEL
lilliepy_query-0.1.dist-info/top_level.txt
lilliepy_query-0.1.dist-info/RECORD
