Metadata-Version: 2.1
Name: lilliepy-query
Version: 0.1
Summary: fetching library for fetching and caching data for the Lilliepy Framework
Home-page: https://github.com/websitedeb/lilliepy-query
Author: Sarthak Ghoshal
Author-email: sarthak22.ghoshal@gmail.com
License: MIT
Keywords: lilliepy,lilliepy-query,reactpy
Classifier: Programming Language :: Python :: 3
Classifier: License :: OSI Approved :: MIT License
Classifier: Operating System :: OS Independent
Requires-Python: >=3.6
Requires-Dist: reactpy
Requires-Dist: asyncio
